LibcSearcher2/__init__.py
LibcSearcher2-0.2.1555593723.dist-info/LICENSE
LibcSearcher2-0.2.1555593723.dist-info/METADATA
LibcSearcher2-0.2.1555593723.dist-info/WHEEL
LibcSearcher2-0.2.1555593723.dist-info/top_level.txt
LibcSearcher2-0.2.1555593723.dist-info/RECORD
