Metadata-Version: 2.1
Name: LibcSearcher2
Version: 0.2.1555593723
Summary: LibcSearcher2: Maybe a faster LibcSearcher
Home-page: https://github.com/TooYoungTooSimp/LibcSearcher2
Author: TooYoungTooSimp
Author-email: 6648049+TooYoungTooSimp@users.noreply.github.com
License: UNKNOWN
Platform: UNKNOWN
Classifier: Programming Language :: Python
Classifier: Topic :: Security
